{
  "main_menu": [
    {
      "module": "japanese-syllabary",
      "furigana": "ごじゅうおん",
      "kanji": "五十音",
      "local_lang": "Японский алфавит",
      "icon": "あ"
    },
    {
      "module": "new-words",
      "furigana": "あたらしいことば",
      "kanji": "新しい言葉",
      "local_lang": "Новые слова",
      "icon": "spellcheck"
    },
    {
      "module": "japanese-characters",
      "furigana": "かんじ",
      "kanji": "漢字",
      "local_lang": "Иероглифы",
      "icon": "字"
    },
    {
      "module": "practice",
      "furigana": "れんしゅう",
      "kanji": "練習",
      "local_lang": "Практика",
      "icon": "subject"
    }
  ],
  "japanese_syllabary": [
    {
      "module": "hiragana",
      "furigana": "ひらがな",
      "local_lang": "Хирагана"
    },
    {
      "module": "katakana",
      "furigana": "カタカナ",
      "local_lang": "Катакана"
    }
  ],
  "practice": [
    {
      "module": "practice/hiragana/gojuon",
      "local_lang": "Практика по хирагане: основные символы 五十音",
      "enum": "１"
    },
    {
      "module": "practice/hiragana/additional-symbols",
      "local_lang": "Практика по хирагане: дополнительные символы",
      "enum": "２"
    },
    {
      "module": "practice/hiragana/yoon",
      "local_lang": "Практика по хирагане: 拗音",
      "enum": "３"
    },
    {
      "module": "practice/katakana",
      "furigana": "カタカナのれんしゅう",
      "kanji": "カタカナの練習で",
      "local_lang": "Практика по катакане",
      "enum": "４"
    }
  ]
}